vpcrouter/__init__.py
vpcrouter/currentstate/__init__.py
vpcrouter/errors/__init__.py
vpcrouter/main/__init__.py
vpcrouter/main/http_server.py
vpcrouter/monitor/__init__.py
vpcrouter/monitor/common.py
vpcrouter/monitor/plugins/__init__.py
vpcrouter/monitor/plugins/always.py
vpcrouter/monitor/plugins/icmpecho.py
vpcrouter/monitor/plugins/multi.py
vpcrouter/monitor/plugins/tcp.py
vpcrouter/plugin_framework/__init__.py
vpcrouter/tests/__init__.py
vpcrouter/tests/test_common.py
vpcrouter/tests/test_http_server.py
vpcrouter/tests/test_main.py
vpcrouter/tests/test_monitor.py
vpcrouter/tests/test_utils.py
vpcrouter/tests/test_vpc.py
vpcrouter/tests/test_watcher.py
vpcrouter/utils/__init__.py
vpcrouter/vpc/__init__.py
vpcrouter/watcher/__init__.py
vpcrouter/watcher/common.py
vpcrouter/watcher/plugins/__init__.py
vpcrouter/watcher/plugins/configfile.py
vpcrouter/watcher/plugins/fixedconf.py
vpcrouter/watcher/plugins/http.py
vpcrouter-1.8.11.dist-info/DESCRIPTION.rst
vpcrouter-1.8.11.dist-info/METADATA
vpcrouter-1.8.11.dist-info/RECORD
vpcrouter-1.8.11.dist-info/WHEEL
vpcrouter-1.8.11.dist-info/entry_points.txt
vpcrouter-1.8.11.dist-info/metadata.json
vpcrouter-1.8.11.dist-info/top_level.txt
