Metadata-Version: 2.0
Name: vpcrouter
Version: 1.8.11
Summary: Automated route management, backup routes and route failover for Amazon VPC environments
Home-page: http://github.com/romana/vpc-router/
Author: Juergen Brendel
Author-email: jbrendel@paninetworks.com
License: Apache Software License
Platform: UNKNOWN
Classifier: Programming Language :: Python
Classifier: Natural Language :: English
Classifier: Environment :: No Input/Output (Daemon)
Classifier: Intended Audience :: System Administrators
Classifier: License :: OSI Approved :: Apache Software License
Classifier: Operating System :: POSIX :: Linux
Classifier: Topic :: System :: Clustering
Classifier: Topic :: System :: Networking
Requires-Dist: argparse (==1.2.1)
Requires-Dist: boto (==2.47.0)
Requires-Dist: bottle (==0.12.13)
Requires-Dist: ipaddress (>=1.0.17)
Requires-Dist: multiping (>=1.0.4)
Requires-Dist: netaddr (==0.7.19)
Requires-Dist: watchdog (==0.8.3)
Requires-Dist: wsgiref (==0.1.2)
